text_hr/__init__.py
text_hr/adjectives.py
text_hr/base.py
text_hr/detect.py
text_hr/fix_words.py
text_hr/morphs.py
text_hr/nouns.py
text_hr/nums.py
text_hr/pronouns.py
text_hr/utils.py
text_hr/verbs.py
text_hr/vocals.py
text_hr-0.20.dist-info/LICENCE
text_hr-0.20.dist-info/METADATA
text_hr-0.20.dist-info/WHEEL
text_hr-0.20.dist-info/top_level.txt
text_hr-0.20.dist-info/RECORD
